noober/__init__.py
noober/__main__.py
noober-0.0.1.dist-info/LICENSE
noober-0.0.1.dist-info/METADATA
noober-0.0.1.dist-info/WHEEL
noober-0.0.1.dist-info/top_level.txt
noober-0.0.1.dist-info/RECORD
