Metadata-Version: 2.1
Name: noober
Version: 0.0.1
Summary: A Simple Library for Beginners and Advance Users a like, to make writing scripts a bit easier
Home-page: https://github.com/newtoallofthis123/noober
Author: NoobScience
Author-email: noobscience123@gmail.com
License: MIT
Project-URL: Author WebSite, https://newtoallofthis123.github.io/About
Project-URL: Bug Tracker, https://github.com/newtoallofthis123/noober/issues
Platform: UNKNOWN
Classifier: License :: OSI Approved :: MIT License
Classifier: Programming Language :: Python :: 3
Classifier: Programming Language :: Python :: 3.7
Requires-Python: >=3.6
License-File: LICENSE
Requires-Dist: pyperclip
Requires-Dist: requests
